foureg/__init__.py
foureg/constraints.py
foureg/imreg.py
foureg/result.py
foureg/utils.py
foureg-1.0.0.dist-info/LICENSE
foureg-1.0.0.dist-info/METADATA
foureg-1.0.0.dist-info/WHEEL
foureg-1.0.0.dist-info/RECORD
