Metadata-Version: 2.1
Name: foureg
Version: 1.0.0
Summary: Fourier transform based image registration
Home-page: https://github.com/GCBallesteros/foureg
Keywords: image registration,image
Author: Guillem Ballesteros
Author-email: guillem@maxwellrules.com
Requires-Python: >=3.8,<3.12
Classifier: Intended Audience :: Science/Research
Classifier: License :: OSI Approved :: BSD License
Classifier: Operating System :: OS Independent
Classifier: Programming Language :: Python
Classifier: Programming Language :: Python :: 3
Classifier: Programming Language :: Python :: 3.8
Classifier: Programming Language :: Python :: 3.9
Classifier: Programming Language :: Python :: 3.10
Classifier: Programming Language :: Python :: 3.11
Classifier: Programming Language :: Python :: 3 :: Only
Classifier: Topic :: Scientific/Engineering :: Image Recognition
Classifier: Topic :: Utilities
Requires-Dist: numpy (>=1.21,<2.0)
Requires-Dist: torch (>=2.0.1,<3.0.0)
Project-URL: Repository, https://github.com/GCBallesteros/foureg
